README.rst
setup.py
email_quick_signup/__init__.py
email_quick_signup/adapter.py
email_quick_signup/admin.py
email_quick_signup/app_settings.py
email_quick_signup/forms.py
email_quick_signup/managers.py
email_quick_signup/models.py
email_quick_signup/signals.py
email_quick_signup/status.py
email_quick_signup/urls.py
email_quick_signup/utils.py
email_quick_signup/validators.py
email_quick_signup/views.py
email_quick_signup/locale/__init__.py
email_quick_signup/locale/zh_Hans/__init__.py
email_quick_signup/locale/zh_Hans/LC_MESSAGES/django.po
email_quick_signup/migrations/0001_initial.py
email_quick_signup/migrations/__init__.py
email_quick_signup/templates/__init__.py
email_quick_signup/templates/email/email_confirmation_message.html
email_quick_signup/templates/email/email_confirmation_signup_message.html
email_quick_signup/templates/email/email_confirmation_signup_subject.txt
email_quick_signup/templates/email/email_confirmation_subject.txt
lettoo_email_quick_signup.egg-info/PKG-INFO
lettoo_email_quick_signup.egg-info/SOURCES.txt
lettoo_email_quick_signup.egg-info/SOURCES.txt.py
lettoo_email_quick_signup.egg-info/dependency_links.txt
lettoo_email_quick_signup.egg-info/dependency_links.txt.py
lettoo_email_quick_signup.egg-info/not-zip-safe
lettoo_email_quick_signup.egg-info/requires.txt
lettoo_email_quick_signup.egg-info/requires.txt.py
lettoo_email_quick_signup.egg-info/top_level.txt
lettoo_email_quick_signup.egg-info/top_level.txt.py